campubtest/__init__.py
campubtest/__main__.py
campubtest/src/__init__.py
campubtest/src/utils.py
campubtest-0.1.2.dist-info/LICENSE
campubtest-0.1.2.dist-info/METADATA
campubtest-0.1.2.dist-info/WHEEL
campubtest-0.1.2.dist-info/entry_points.txt
campubtest-0.1.2.dist-info/RECORD
